pygooglechat/__init__.py
pygooglechat/google_chat.py
pygooglechat/response.py
pygooglechat-0.3.dist-info/LICENSE
pygooglechat-0.3.dist-info/METADATA
pygooglechat-0.3.dist-info/WHEEL
pygooglechat-0.3.dist-info/top_level.txt
pygooglechat-0.3.dist-info/RECORD
