Metadata-Version: 2.1
Name: pygooglechat
Version: 0.3
Summary: Easy Googlechat Handler
Home-page: https://github.com/moonseoklee/pygooglechat
Author: moonseoklee
Author-email: winnyiee@korea.ac.kr
License: UNKNOWN
Platform: UNKNOWN
Classifier: Programming Language :: Python :: 3
Classifier: License :: OSI Approved :: MIT License
Classifier: Operating System :: OS Independent
Requires-Python: >=3
License-File: LICENSE
